Metadata-Version: 2.1
Name: matrixgg
Version: 0.6
Summary: Solve matrix by Gaussian and Jacoby
Home-page: UNKNOWN
Author-email: shpeka4kaps4@mail.ru
License: UNKNOWN
Platform: UNKNOWN
